{
  "form": "i-129s",
  "source": "USCIS forms printed/i-129s.pdf",
  "output": "generated-filled/i-129s-output.pdf",
  "fields": [
    {
      "key": "Pt1Line1_NameofBusinessorOrgName",
      "originalKey": "form1[0].#subform[0].Pt1Line1_NameofBusinessorOrgName[0]",
      "kind": "text",
      "mode": "text",
      "page": 1,
      "x": 60,
      "y": 398,
      "width": 234,
      "height": 18,
      "size": 10,
      "font": "CourierBold"
    },
    {
      "key": "Pt1Line3_Checkbox",
      "originalKeys": [
        "form1[0].#subform[0].Pt1Line3_Checkbox[0]",
        "form1[0].#subform[0].Pt1Line3_Checkbox[1]"
      ],
      "kind": "checkbox",
      "mode": "checkbox_group",
      "page": 1,
      "size": 10,
      "font": "HelveticaBold",
      "options": [
        {
          "value": 0,
          "x": 216,
          "y": 192,
          "width": 10,
          "height": 10
        },
        {
          "value": 1,
          "x": 258,
          "y": 192,
          "width": 10,
          "height": 10
        }
      ]
    },
    {
      "key": "Pt1Line8_WebsiteAddress",
      "originalKey": "form1[0].#subform[0].Pt1Line8_WebsiteAddress[0]",
      "kind": "text",
      "mode": "text",
      "page": 1,
      "x": 342,
      "y": 176,
      "width": 234,
      "height": 18,
      "size": 10,
      "font": "CourierBold"
    },
    {
      "key": "Pt1Line7_EmailAddress",
      "originalKey": "form1[0].#subform[0].Pt1Line7_EmailAddress[0]",
      "kind": "text",
      "mode": "text",
      "page": 1,
      "x": 342,
      "y": 212,
      "width": 234,
      "height": 18,
      "size": 10,
      "font": "CourierBold"
    },
    {
      "key": "Pt1Line6_FaxNumber",
      "originalKey": "form1[0].#subform[0].Pt1Line6_FaxNumber[0]",
      "kind": "text",
      "mode": "text",
      "page": 1,
      "x": 342,
      "y": 248,
      "width": 234,
      "height": 18,
      "size": 10,
      "font": "CourierBold"
    },
    {
      "key": "Pt1Line5_DaytimeTelephoneNumber",
      "originalKey": "form1[0].#subform[0].Pt1Line5_DaytimeTelephoneNumber[0]",
      "kind": "text",
      "mode": "text",
      "page": 1,
      "x": 342,
      "y": 284,
      "width": 234,
      "height": 18,
      "size": 10,
      "font": "CourierBold"
    },
    {
      "key": "USCISOnlineAcctNumber",
      "originalKey": "form1[0].#subform[0].#area[0].USCISOnlineAcctNumber[0]",
      "kind": "text",
      "mode": "text",
      "page": 1,
      "x": 396,
      "y": 492,
      "width": 174,
      "height": 18,
      "size": 10,
      "font": "CourierBold"
    },
    {
      "key": "AttorneyStateBarNumber",
      "originalKey": "form1[0].#subform[0].AttorneyStateBarNumber[0]",
      "kind": "text",
      "mode": "text",
      "page": 1,
      "x": 264,
      "y": 492,
      "width": 120,
      "height": 18,
      "size": 10,
      "font": "CourierBold"
    },
    {
      "key": "CheckBox1",
      "originalKey": "form1[0].#subform[0].CheckBox1[0]",
      "kind": "checkbox",
      "mode": "checkbox_single",
      "page": 1,
      "x": 152.8,
      "y": 520,
      "width": 10,
      "height": 10,
      "size": 10,
      "font": "HelveticaBold"
    },
    {
      "key": "Pt1Line9_Checkbox",
      "originalKeys": [
        "form1[0].#subform[0].Pt1Line9_Checkbox[0]",
        "form1[0].#subform[0].Pt1Line9_Checkbox[1]"
      ],
      "kind": "checkbox",
      "mode": "checkbox_group",
      "page": 1,
      "size": 10,
      "font": "HelveticaBold",
      "options": [
        {
          "value": 0,
          "x": 498,
          "y": 114,
          "width": 10,
          "height": 10
        },
        {
          "value": 1,
          "x": 540,
          "y": 114,
          "width": 10,
          "height": 10
        }
      ]
    },
    {
      "key": "Pt1Line2a_InCareofName",
      "originalKey": "form1[0].#subform[0].Pt1Line2a_InCareofName[0]",
      "kind": "text",
      "mode": "text",
      "page": 1,
      "x": 60,
      "y": 332,
      "width": 234.1,
      "height": 18,
      "size": 10,
      "font": "CourierBold"
    },
    {
      "key": "Pt1Line2b_StreetNumberName",
      "originalKey": "form1[0].#subform[0].Pt1Line2b_StreetNumberName[0]",
      "kind": "text",
      "mode": "text",
      "page": 1,
      "x": 126,
      "y": 308,
      "width": 168,
      "height": 18,
      "size": 10,
      "font": "CourierBold"
    },
    {
      "key": "Pt1Line2c_Unit",
      "originalKeys": [
        "form1[0].#subform[0].Pt1Line2c_Unit[0]",
        "form1[0].#subform[0].Pt1Line2c_Unit[1]",
        "form1[0].#subform[0].Pt1Line2c_Unit[2]"
      ],
      "kind": "checkbox",
      "mode": "checkbox_group",
      "page": 1,
      "size": 10,
      "font": "HelveticaBold",
      "options": [
        {
          "value": 0,
          "x": 102,
          "y": 288,
          "width": 10,
          "height": 10
        },
        {
          "value": 1,
          "x": 144,
          "y": 288,
          "width": 10,
          "height": 10
        },
        {
          "value": 2,
          "x": 60,
          "y": 288,
          "width": 10,
          "height": 10
        }
      ]
    },
    {
      "key": "Pt1Line2c_AptSteFlrNumber",
      "originalKey": "form1[0].#subform[0].Pt1Line2c_AptSteFlrNumber[0]",
      "kind": "text",
      "mode": "text",
      "page": 1,
      "x": 186,
      "y": 284,
      "width": 108,
      "height": 18,
      "size": 10,
      "font": "CourierBold"
    },
    {
      "key": "Pt1Line2d_CityOrTown",
      "originalKey": "form1[0].#subform[0].Pt1Line2d_CityOrTown[0]",
      "kind": "text",
      "mode": "text",
      "page": 1,
      "x": 126,
      "y": 260,
      "width": 168,
      "height": 18,
      "size": 10,
      "font": "CourierBold"
    },
    {
      "key": "Pt1Line2f_ZipCode",
      "originalKey": "form1[0].#subform[0].Pt1Line2f_ZipCode[0]",
      "kind": "text",
      "mode": "text",
      "page": 1,
      "x": 192,
      "y": 236,
      "width": 102,
      "height": 18,
      "size": 10,
      "font": "CourierBold"
    },
    {
      "key": "Pt1Line2e_State",
      "originalKey": "form1[0].#subform[0].Pt1Line2e_State[0]",
      "kind": "dropdown",
      "mode": "dropdown",
      "page": 1,
      "x": 84,
      "y": 236,
      "width": 36,
      "height": 18,
      "size": 10,
      "font": "CourierBold"
    },
    {
      "key": "Pt1Line4b_Unit",
      "originalKeys": [
        "form1[0].#subform[0].Pt1Line4b_Unit[0]",
        "form1[0].#subform[0].Pt1Line4b_Unit[1]",
        "form1[0].#subform[0].Pt1Line4b_Unit[2]"
      ],
      "kind": "checkbox",
      "mode": "checkbox_group",
      "page": 1,
      "size": 10,
      "font": "HelveticaBold",
      "options": [
        {
          "value": 0,
          "x": 384,
          "y": 402,
          "width": 10,
          "height": 10
        },
        {
          "value": 1,
          "x": 426,
          "y": 402,
          "width": 10,
          "height": 10
        },
        {
          "value": 2,
          "x": 342,
          "y": 402,
          "width": 10,
          "height": 10
        }
      ]
    },
    {
      "key": "Pt1Line4b_AptSteFlrNumber",
      "originalKey": "form1[0].#subform[0].Pt1Line4b_AptSteFlrNumber[0]",
      "kind": "text",
      "mode": "text",
      "page": 1,
      "x": 468,
      "y": 398,
      "width": 108,
      "height": 18,
      "size": 10,
      "font": "CourierBold"
    },
    {
      "key": "Pt1Line4c_CityOrTown",
      "originalKey": "form1[0].#subform[0].Pt1Line4c_CityOrTown[0]",
      "kind": "text",
      "mode": "text",
      "page": 1,
      "x": 408,
      "y": 374,
      "width": 168,
      "height": 18,
      "size": 10,
      "font": "CourierBold"
    },
    {
      "key": "Pt1Line4e_ZipCode",
      "originalKey": "form1[0].#subform[0].Pt1Line4e_ZipCode[0]",
      "kind": "text",
      "mode": "text",
      "page": 1,
      "x": 474,
      "y": 350,
      "width": 102,
      "height": 18,
      "size": 10,
      "font": "CourierBold"
    },
    {
      "key": "Pt1Line4d_State",
      "originalKey": "form1[0].#subform[0].Pt1Line4d_State[0]",
      "kind": "dropdown",
      "mode": "dropdown",
      "page": 1,
      "x": 366,
      "y": 350,
      "width": 36,
      "height": 18,
      "size": 10,
      "font": "CourierBold"
    },
    {
      "key": "Pt1Line4a_StreetNumberName",
      "originalKey": "form1[0].#subform[0].Pt1Line4a_StreetNumberName[0]",
      "kind": "text",
      "mode": "text",
      "page": 1,
      "x": 408,
      "y": 422,
      "width": 168,
      "height": 18,
      "size": 10,
      "font": "CourierBold"
    },
    {
      "key": "Pt3Line4a_FamilyName",
      "originalKey": "form1[0].#subform[1].Pt3Line4a_FamilyName[0]",
      "kind": "text",
      "mode": "text",
      "page": 2,
      "x": 402,
      "y": 428,
      "width": 174,
      "height": 18,
      "size": 10,
      "font": "CourierBold"
    },
    {
      "key": "Pt3Line4b_GivenName",
      "originalKey": "form1[0].#subform[1].Pt3Line4b_GivenName[0]",
      "kind": "text",
      "mode": "text",
      "page": 2,
      "x": 402,
      "y": 404,
      "width": 174,
      "height": 18,
      "size": 10,
      "font": "CourierBold"
    },
    {
      "key": "Pt3Line4c_MiddleName",
      "originalKey": "form1[0].#subform[1].Pt3Line4c_MiddleName[0]",
      "kind": "text",
      "mode": "text",
      "page": 2,
      "x": 402,
      "y": 380,
      "width": 174,
      "height": 18,
      "size": 10,
      "font": "CourierBold"
    },
    {
      "key": "Pt2Line5a_FamilyName",
      "originalKey": "form1[0].#subform[1].Pt2Line5a_FamilyName[0]",
      "kind": "text",
      "mode": "text",
      "page": 2,
      "x": 402,
      "y": 272,
      "width": 174,
      "height": 18,
      "size": 10,
      "font": "CourierBold"
    },
    {
      "key": "Pt2Line5b_GivenName",
      "originalKey": "form1[0].#subform[1].Pt2Line5b_GivenName[0]",
      "kind": "text",
      "mode": "text",
      "page": 2,
      "x": 402,
      "y": 248,
      "width": 174,
      "height": 18,
      "size": 10,
      "font": "CourierBold"
    },
    {
      "key": "Pt2Line5c_MiddleName",
      "originalKey": "form1[0].#subform[1].Pt2Line5c_MiddleName[0]",
      "kind": "text",
      "mode": "text",
      "page": 2,
      "x": 402,
      "y": 224,
      "width": 174,
      "height": 18,
      "size": 10,
      "font": "CourierBold"
    },
    {
      "key": "Pt3Line1_CheckBox",
      "originalKeys": [
        "form1[0].#subform[1].Pt3Line1_CheckBox[0]",
        "form1[0].#subform[1].Pt3Line1_CheckBox[1]"
      ],
      "kind": "checkbox",
      "mode": "checkbox_group",
      "page": 2,
      "size": 10,
      "font": "HelveticaBold",
      "options": [
        {
          "value": 0,
          "x": 61,
          "y": 504,
          "width": 10,
          "height": 10
        },
        {
          "value": 1,
          "x": 61,
          "y": 486,
          "width": 10,
          "height": 10
        }
      ]
    },
    {
      "key": "Pt3Line5a_DateFrom",
      "originalKey": "form1[0].#subform[1].Pt3Line5a_DateFrom[0]",
      "kind": "text",
      "mode": "text",
      "page": 2,
      "x": 210,
      "y": 410,
      "width": 84,
      "height": 18,
      "size": 10,
      "font": "CourierBold"
    },
    {
      "key": "Pt3Line5b_DateTo",
      "originalKey": "form1[0].#subform[1].Pt3Line5b_DateTo[0]",
      "kind": "text",
      "mode": "text",
      "page": 2,
      "x": 210,
      "y": 386,
      "width": 84,
      "height": 18,
      "size": 10,
      "font": "CourierBold"
    },
    {
      "key": "Pt3Line10a_DateFrom",
      "originalKey": "form1[0].#subform[1].Pt3Line10a_DateFrom[0]",
      "kind": "text",
      "mode": "text",
      "page": 2,
      "x": 210,
      "y": 188,
      "width": 84,
      "height": 18,
      "size": 10,
      "font": "CourierBold"
    },
    {
      "key": "Pt3Line10b_DateTo",
      "originalKey": "form1[0].#subform[1].Pt3Line10b_DateTo[0]",
      "kind": "text",
      "mode": "text",
      "page": 2,
      "x": 210,
      "y": 164,
      "width": 84,
      "height": 18,
      "size": 10,
      "font": "CourierBold"
    },
    {
      "key": "Pt3Line11_NonimmigrantStatus",
      "originalKey": "form1[0].#subform[1].Pt3Line11_NonimmigrantStatus[0]",
      "kind": "text",
      "mode": "text",
      "page": 2,
      "x": 60,
      "y": 128,
      "width": 234,
      "height": 18,
      "size": 10,
      "font": "CourierBold"
    },
    {
      "key": "Pt3Line1_AlienNumber",
      "originalKey": "form1[0].#subform[1].#area[1].Pt3Line1_AlienNumber[0]",
      "kind": "text",
      "mode": "text",
      "page": 2,
      "x": 446.8,
      "y": 554,
      "width": 129,
      "height": 18,
      "size": 10,
      "font": "CourierBold"
    },
    {
      "key": "Pt2Line2_USCISELISAcctNumber",
      "originalKey": "form1[0].#subform[1].#area[2].Pt2Line2_USCISELISAcctNumber[0]",
      "kind": "text",
      "mode": "text",
      "page": 2,
      "x": 402,
      "y": 518,
      "width": 174,
      "height": 18,
      "size": 10,
      "font": "CourierBold"
    },
    {
      "key": "Pt2Line3_SSN",
      "originalKey": "form1[0].#subform[1].#area[3].Pt2Line3_SSN[0]",
      "kind": "text",
      "mode": "text",
      "page": 2,
      "x": 447,
      "y": 482,
      "width": 129,
      "height": 18,
      "size": 10,
      "font": "CourierBold"
    },
    {
      "key": "Pt2Line3_Checkbox",
      "originalKeys": [
        "form1[0].#subform[1].Pt2Line3_Checkbox[0]",
        "form1[0].#subform[1].Pt2Line3_Checkbox[1]"
      ],
      "kind": "checkbox",
      "mode": "checkbox_group",
      "page": 2,
      "size": 10,
      "font": "HelveticaBold",
      "options": [
        {
          "value": 0,
          "x": 258,
          "y": 324,
          "width": 10,
          "height": 10
        },
        {
          "value": 1,
          "x": 216,
          "y": 324,
          "width": 10,
          "height": 10
        }
      ]
    },
    {
      "key": "Pt1Line10_Checkbox",
      "originalKeys": [
        "form1[0].#subform[1].Pt1Line10_Checkbox[0]",
        "form1[0].#subform[1].Pt1Line10_Checkbox[1]"
      ],
      "kind": "checkbox",
      "mode": "checkbox_group",
      "page": 2,
      "size": 10,
      "font": "HelveticaBold",
      "options": [
        {
          "value": 0,
          "x": 258,
          "y": 666,
          "width": 10,
          "height": 10
        },
        {
          "value": 1,
          "x": 216,
          "y": 666,
          "width": 10,
          "height": 10
        }
      ]
    },
    {
      "key": "Pt3Line12a_DateFrom",
      "originalKey": "form1[0].#subform[1].Pt3Line12a_DateFrom[0]",
      "kind": "text",
      "mode": "text",
      "page": 2,
      "x": 492,
      "y": 704,
      "width": 84,
      "height": 18,
      "size": 10,
      "font": "CourierBold"
    },
    {
      "key": "Pt3Line12b_DateTo",
      "originalKey": "form1[0].#subform[1].Pt3Line12b_DateTo[0]",
      "kind": "text",
      "mode": "text",
      "page": 2,
      "x": 492,
      "y": 680,
      "width": 84,
      "height": 18,
      "size": 10,
      "font": "CourierBold"
    },
    {
      "key": "Pt3Line13_NonimmigrantStatus",
      "originalKey": "form1[0].#subform[1].Pt3Line13_NonimmigrantStatus[0]",
      "kind": "text",
      "mode": "text",
      "page": 2,
      "x": 342,
      "y": 644,
      "width": 234,
      "height": 18,
      "size": 10,
      "font": "CourierBold"
    },
    {
      "key": "Pt3Line6b_StreetNumberName",
      "originalKey": "form1[0].#subform[2].Pt3Line6b_StreetNumberName[0]",
      "kind": "text",
      "mode": "text",
      "page": 3,
      "x": 60,
      "y": 608,
      "width": 234,
      "height": 18,
      "size": 10,
      "font": "CourierBold"
    },
    {
      "key": "Pt3Line6c_Unit",
      "originalKeys": [
        "form1[0].#subform[2].Pt3Line6c_Unit[0]",
        "form1[0].#subform[2].Pt3Line6c_Unit[1]",
        "form1[0].#subform[2].Pt3Line6c_Unit[2]"
      ],
      "kind": "checkbox",
      "mode": "checkbox_group",
      "page": 3,
      "size": 10,
      "font": "HelveticaBold",
      "options": [
        {
          "value": 0,
          "x": 102,
          "y": 588,
          "width": 10,
          "height": 10
        },
        {
          "value": 1,
          "x": 144,
          "y": 588,
          "width": 10,
          "height": 10
        },
        {
          "value": 2,
          "x": 60,
          "y": 588,
          "width": 10,
          "height": 10
        }
      ]
    },
    {
      "key": "Pt3Line6c_AptSteFlrNumber",
      "originalKey": "form1[0].#subform[2].Pt3Line6c_AptSteFlrNumber[0]",
      "kind": "text",
      "mode": "text",
      "page": 3,
      "x": 186,
      "y": 584,
      "width": 108,
      "height": 18,
      "size": 10,
      "font": "CourierBold"
    },
    {
      "key": "Pt3Line6d_CityOrTown",
      "originalKey": "form1[0].#subform[2].Pt3Line6d_CityOrTown[0]",
      "kind": "text",
      "mode": "text",
      "page": 3,
      "x": 126,
      "y": 560,
      "width": 168,
      "height": 18,
      "size": 10,
      "font": "CourierBold"
    },
    {
      "key": "Pt3Line6e_Province",
      "originalKey": "form1[0].#subform[2].Pt3Line6e_Province[0]",
      "kind": "text",
      "mode": "text",
      "page": 3,
      "x": 126,
      "y": 536,
      "width": 168,
      "height": 18,
      "size": 10,
      "font": "CourierBold"
    },
    {
      "key": "Pt3Line6f_PostalCode",
      "originalKey": "form1[0].#subform[2].Pt3Line6f_PostalCode[0]",
      "kind": "text",
      "mode": "text",
      "page": 3,
      "x": 126,
      "y": 512,
      "width": 168,
      "height": 18,
      "size": 10,
      "font": "CourierBold"
    },
    {
      "key": "Pt3Line6g_Country",
      "originalKey": "form1[0].#subform[2].Pt3Line6g_Country[0]",
      "kind": "text",
      "mode": "text",
      "page": 3,
      "x": 60,
      "y": 476,
      "width": 234,
      "height": 18,
      "size": 10,
      "font": "CourierBold"
    },
    {
      "key": "Pt3Line6a_InCareofName",
      "originalKey": "form1[0].#subform[2].Pt3Line6a_InCareofName[0]",
      "kind": "text",
      "mode": "text",
      "page": 3,
      "x": 60,
      "y": 644,
      "width": 234,
      "height": 18,
      "size": 10,
      "font": "CourierBold"
    },
    {
      "key": "Pt3Line7_Checkbox",
      "originalKeys": [
        "form1[0].#subform[2].Pt3Line7_Checkbox[0]",
        "form1[0].#subform[2].Pt3Line7_Checkbox[1]"
      ],
      "kind": "checkbox",
      "mode": "checkbox_group",
      "page": 3,
      "size": 10,
      "font": "HelveticaBold",
      "options": [
        {
          "value": 0,
          "x": 216,
          "y": 444,
          "width": 10,
          "height": 10
        },
        {
          "value": 1,
          "x": 258,
          "y": 444,
          "width": 10,
          "height": 10
        }
      ]
    },
    {
      "key": "Pt2Line14_CitzorNationality",
      "originalKey": "form1[0].#subform[2].Pt2Line14_CitzorNationality[0]",
      "kind": "text",
      "mode": "text",
      "page": 3,
      "x": 342,
      "y": 530,
      "width": 234,
      "height": 18,
      "size": 10,
      "font": "CourierBold"
    },
    {
      "key": "Pt2Line13_CountryofBirth",
      "originalKey": "form1[0].#subform[2].Pt2Line13_CountryofBirth[0]",
      "kind": "text",
      "mode": "text",
      "page": 3,
      "x": 342,
      "y": 566,
      "width": 234,
      "height": 18,
      "size": 10,
      "font": "CourierBold"
    },
    {
      "key": "Pt3Line8a_StreetNumberName",
      "originalKey": "form1[0].#subform[2].Pt3Line8a_StreetNumberName[0]",
      "kind": "text",
      "mode": "text",
      "page": 3,
      "x": 126,
      "y": 356,
      "width": 168,
      "height": 18,
      "size": 10,
      "font": "CourierBold"
    },
    {
      "key": "Pt3Line8b_Unit",
      "originalKeys": [
        "form1[0].#subform[2].Pt3Line8b_Unit[0]",
        "form1[0].#subform[2].Pt3Line8b_Unit[1]",
        "form1[0].#subform[2].Pt3Line8b_Unit[2]"
      ],
      "kind": "checkbox",
      "mode": "checkbox_group",
      "page": 3,
      "size": 10,
      "font": "HelveticaBold",
      "options": [
        {
          "value": 0,
          "x": 102,
          "y": 336,
          "width": 10,
          "height": 10
        },
        {
          "value": 1,
          "x": 144,
          "y": 336,
          "width": 10,
          "height": 10
        },
        {
          "value": 2,
          "x": 60,
          "y": 336,
          "width": 10,
          "height": 10
        }
      ]
    },
    {
      "key": "Pt3Line8b_AptSteFlrNumber",
      "originalKey": "form1[0].#subform[2].Pt3Line8b_AptSteFlrNumber[0]",
      "kind": "text",
      "mode": "text",
      "page": 3,
      "x": 186,
      "y": 332,
      "width": 108,
      "height": 18,
      "size": 10,
      "font": "CourierBold"
    },
    {
      "key": "Pt3Line8c_CityOrTown",
      "originalKey": "form1[0].#subform[2].Pt3Line8c_CityOrTown[0]",
      "kind": "text",
      "mode": "text",
      "page": 3,
      "x": 126,
      "y": 308,
      "width": 168,
      "height": 18,
      "size": 10,
      "font": "CourierBold"
    },
    {
      "key": "Pt3Line8d_Province",
      "originalKey": "form1[0].#subform[2].Pt3Line8d_Province[0]",
      "kind": "text",
      "mode": "text",
      "page": 3,
      "x": 126,
      "y": 284,
      "width": 167.9,
      "height": 18,
      "size": 10,
      "font": "CourierBold"
    },
    {
      "key": "Pt3Line8e_PostalCode",
      "originalKey": "form1[0].#subform[2].Pt3Line8e_PostalCode[0]",
      "kind": "text",
      "mode": "text",
      "page": 3,
      "x": 126,
      "y": 260,
      "width": 167.9,
      "height": 18,
      "size": 10,
      "font": "CourierBold"
    },
    {
      "key": "Pt3Line8f_Country",
      "originalKey": "form1[0].#subform[2].Pt3Line8f_Country[0]",
      "kind": "text",
      "mode": "text",
      "page": 3,
      "x": 60,
      "y": 224,
      "width": 234,
      "height": 18,
      "size": 10,
      "font": "CourierBold"
    },
    {
      "key": "Pt2Line10_Gender",
      "originalKeys": [
        "form1[0].#subform[2].Pt2Line10_Gender[0]",
        "form1[0].#subform[2].Pt2Line10_Gender[1]"
      ],
      "kind": "checkbox",
      "mode": "checkbox_group",
      "page": 3,
      "size": 10,
      "font": "HelveticaBold",
      "options": [
        {
          "value": 0,
          "x": 440.2,
          "y": 678,
          "width": 10,
          "height": 10
        },
        {
          "value": 1,
          "x": 386.2,
          "y": 678,
          "width": 10,
          "height": 10
        }
      ]
    },
    {
      "key": "Pt2Line11_CityOrTownofBirth",
      "originalKey": "form1[0].#subform[2].Pt2Line11_CityOrTownofBirth[0]",
      "kind": "text",
      "mode": "text",
      "page": 3,
      "x": 342,
      "y": 638,
      "width": 234,
      "height": 18,
      "size": 10,
      "font": "CourierBold"
    },
    {
      "key": "Pt2Line9_DateOfBirth",
      "originalKey": "form1[0].#subform[2].Pt2Line9_DateOfBirth[0]",
      "kind": "text",
      "mode": "text",
      "page": 3,
      "x": 492,
      "y": 698,
      "width": 84,
      "height": 18,
      "size": 10,
      "font": "CourierBold"
    },
    {
      "key": "Pt2Line12_ProvinceofBirth",
      "originalKey": "form1[0].#subform[2].Pt2Line12_ProvinceofBirth[0]",
      "kind": "text",
      "mode": "text",
      "page": 3,
      "x": 342,
      "y": 602,
      "width": 234,
      "height": 18,
      "size": 10,
      "font": "CourierBold"
    },
    {
      "key": "Pt4Line1_ReceiptNumber",
      "originalKey": "form1[0].#subform[2].#area[4].Pt4Line1_ReceiptNumber[0]",
      "kind": "text",
      "mode": "text",
      "page": 3,
      "x": 387.6,
      "y": 427.9,
      "width": 188.4,
      "height": 18.1,
      "size": 10,
      "font": "CourierBold"
    },
    {
      "key": "Pt3Line3_Checkbox",
      "originalKeys": [
        "form1[0].#subform[2].Pt3Line3_Checkbox[0]",
        "form1[0].#subform[2].Pt3Line3_Checkbox[1]"
      ],
      "kind": "checkbox",
      "mode": "checkbox_group",
      "page": 3,
      "size": 10,
      "font": "HelveticaBold",
      "options": [
        {
          "value": 0,
          "x": 498,
          "y": 399,
          "width": 10,
          "height": 10
        },
        {
          "value": 1,
          "x": 540,
          "y": 399,
          "width": 10,
          "height": 10
        }
      ]
    },
    {
      "key": "Pt4Line3a_StreetNumberName",
      "originalKey": "form1[0].#subform[2].Pt4Line3a_StreetNumberName[0]",
      "kind": "text",
      "mode": "text",
      "page": 3,
      "x": 408,
      "y": 344,
      "width": 168,
      "height": 18,
      "size": 10,
      "font": "CourierBold"
    },
    {
      "key": "Pt4Line3b_Unit",
      "originalKeys": [
        "form1[0].#subform[2].Pt4Line3b_Unit[0]",
        "form1[0].#subform[2].Pt4Line3b_Unit[1]",
        "form1[0].#subform[2].Pt4Line3b_Unit[2]"
      ],
      "kind": "checkbox",
      "mode": "checkbox_group",
      "page": 3,
      "size": 10,
      "font": "HelveticaBold",
      "options": [
        {
          "value": 0,
          "x": 384,
          "y": 324,
          "width": 10,
          "height": 10
        },
        {
          "value": 1,
          "x": 426,
          "y": 324,
          "width": 10,
          "height": 10
        },
        {
          "value": 2,
          "x": 342,
          "y": 324,
          "width": 10,
          "height": 10
        }
      ]
    },
    {
      "key": "Pt4Line3b_AptSteFlrNumber",
      "originalKey": "form1[0].#subform[2].Pt4Line3b_AptSteFlrNumber[0]",
      "kind": "text",
      "mode": "text",
      "page": 3,
      "x": 468,
      "y": 320,
      "width": 108,
      "height": 18,
      "size": 10,
      "font": "CourierBold"
    },
    {
      "key": "Pt4Line3c_CityOrTown",
      "originalKey": "form1[0].#subform[2].Pt4Line3c_CityOrTown[0]",
      "kind": "text",
      "mode": "text",
      "page": 3,
      "x": 408,
      "y": 296,
      "width": 168,
      "height": 18,
      "size": 10,
      "font": "CourierBold"
    },
    {
      "key": "Pt4Line3e_ZipCode",
      "originalKey": "form1[0].#subform[2].Pt4Line3e_ZipCode[0]",
      "kind": "text",
      "mode": "text",
      "page": 3,
      "x": 474,
      "y": 272,
      "width": 102,
      "height": 18,
      "size": 10,
      "font": "CourierBold"
    },
    {
      "key": "Pt4Line3d_State",
      "originalKey": "form1[0].#subform[2].Pt4Line3d_State[0]",
      "kind": "dropdown",
      "mode": "dropdown",
      "page": 3,
      "x": 366,
      "y": 272,
      "width": 36,
      "height": 18,
      "size": 10,
      "font": "CourierBold"
    },
    {
      "key": "Pt3Line9_JobDescription",
      "originalKey": "form1[0].#subform[2].Pt3Line9_JobDescription[0]",
      "kind": "text",
      "mode": "text",
      "page": 3,
      "x": 342,
      "y": 74,
      "width": 234,
      "height": 36,
      "size": 10,
      "font": "CourierBold"
    },
    {
      "key": "Pt3Line6_Wages",
      "originalKey": "form1[0].#subform[2].Pt3Line6_Wages[0]",
      "kind": "text",
      "mode": "text",
      "page": 3,
      "x": 476,
      "y": 152,
      "width": 100,
      "height": 18,
      "size": 10,
      "font": "CourierBold"
    },
    {
      "key": "Pt3Line7_HoursPerWeek",
      "originalKey": "form1[0].#subform[2].Pt3Line7_HoursPerWeek[0]",
      "kind": "text",
      "mode": "text",
      "page": 3,
      "x": 476,
      "y": 128,
      "width": 100,
      "height": 18,
      "size": 10,
      "font": "CourierBold"
    },
    {
      "key": "Pt3Line8_JobTitle",
      "originalKey": "form1[0].#subform[3].Pt3Line8_JobTitle[0]",
      "kind": "text",
      "mode": "text",
      "page": 4,
      "x": 60,
      "y": 572,
      "width": 234,
      "height": 18,
      "size": 10,
      "font": "CourierBold"
    },
    {
      "key": "Pt3Line9_JobDescription",
      "originalKey": "form1[0].#subform[3].Pt3Line9_JobDescription[1]",
      "kind": "text",
      "mode": "text",
      "page": 4,
      "x": 60,
      "y": 518,
      "width": 234,
      "height": 36,
      "size": 10,
      "font": "CourierBold"
    },
    {
      "key": "Pt4Line14_Checkbox",
      "originalKeys": [
        "form1[0].#subform[3].Pt4Line14_Checkbox[0]",
        "form1[0].#subform[3].Pt4Line14_Checkbox[1]"
      ],
      "kind": "checkbox",
      "mode": "checkbox_group",
      "page": 4,
      "size": 10,
      "font": "HelveticaBold",
      "options": [
        {
          "value": 0,
          "x": 216,
          "y": 378,
          "width": 10,
          "height": 10
        },
        {
          "value": 1,
          "x": 258,
          "y": 378,
          "width": 10,
          "height": 10
        }
      ]
    },
    {
      "key": "Pt4Line10b_NatureOfSupv",
      "originalKey": "form1[0].#subform[3].Pt4Line10b_NatureOfSupv[0]",
      "kind": "text",
      "mode": "text",
      "page": 4,
      "x": 60,
      "y": 200,
      "width": 233.9,
      "height": 54,
      "size": 10,
      "font": "CourierBold"
    },
    {
      "key": "Pt4Line10a_SupervisorName",
      "originalKey": "form1[0].#subform[3].Pt4Line10a_SupervisorName[0]",
      "kind": "text",
      "mode": "text",
      "page": 4,
      "x": 60,
      "y": 284,
      "width": 234,
      "height": 18,
      "size": 10,
      "font": "CourierBold"
    },
    {
      "key": "Pt4Line11_Reason",
      "originalKey": "form1[0].#subform[3].Pt4Line11_Reason[0]",
      "kind": "text",
      "mode": "text",
      "page": 4,
      "x": 60,
      "y": 80,
      "width": 234,
      "height": 54,
      "size": 10,
      "font": "CourierBold"
    },
    {
      "key": "Pt5Line1_CheckBox",
      "originalKeys": [
        "form1[0].#subform[3].Pt5Line1_CheckBox[0]",
        "form1[0].#subform[3].Pt5Line1_CheckBox[1]",
        "form1[0].#subform[3].Pt5Line1_CheckBox[2]"
      ],
      "kind": "checkbox",
      "mode": "checkbox_group",
      "page": 4,
      "size": 10,
      "font": "HelveticaBold",
      "options": [
        {
          "value": 0,
          "x": 343,
          "y": 576,
          "width": 10,
          "height": 10
        },
        {
          "value": 1,
          "x": 343,
          "y": 558,
          "width": 10,
          "height": 10
        },
        {
          "value": 2,
          "x": 343,
          "y": 540,
          "width": 10,
          "height": 10
        }
      ]
    },
    {
      "key": "Pt4Line2_ForeignEmployerName",
      "originalKey": "form1[0].#subform[3].Pt4Line2_ForeignEmployerName[0]",
      "kind": "text",
      "mode": "text",
      "page": 4,
      "x": 342,
      "y": 440,
      "width": 234,
      "height": 18,
      "size": 10,
      "font": "CourierBold"
    },
    {
      "key": "Pt4Line3a_StreetNumberName",
      "originalKey": "form1[0].#subform[3].Pt4Line3a_StreetNumberName[1]",
      "kind": "text",
      "mode": "text",
      "page": 4,
      "x": 408,
      "y": 386,
      "width": 168,
      "height": 18,
      "size": 10,
      "font": "CourierBold"
    },
    {
      "key": "Pt5Line3b_Unit",
      "originalKeys": [
        "form1[0].#subform[3].Pt5Line3b_Unit[0]",
        "form1[0].#subform[3].Pt5Line3b_Unit[1]",
        "form1[0].#subform[3].Pt5Line3b_Unit[2]"
      ],
      "kind": "checkbox",
      "mode": "checkbox_group",
      "page": 4,
      "size": 10,
      "font": "HelveticaBold",
      "options": [
        {
          "value": 0,
          "x": 384,
          "y": 366,
          "width": 10,
          "height": 10
        },
        {
          "value": 1,
          "x": 426,
          "y": 366,
          "width": 10,
          "height": 10
        },
        {
          "value": 2,
          "x": 342,
          "y": 366,
          "width": 10,
          "height": 10
        }
      ]
    },
    {
      "key": "Pt5Line3b_AptSteFlrNumber",
      "originalKey": "form1[0].#subform[3].Pt5Line3b_AptSteFlrNumber[0]",
      "kind": "text",
      "mode": "text",
      "page": 4,
      "x": 468,
      "y": 362,
      "width": 108,
      "height": 18,
      "size": 10,
      "font": "CourierBold"
    },
    {
      "key": "Pt4Line3c_CityOrTown",
      "originalKey": "form1[0].#subform[3].Pt4Line3c_CityOrTown[1]",
      "kind": "text",
      "mode": "text",
      "page": 4,
      "x": 408,
      "y": 338,
      "width": 168,
      "height": 18,
      "size": 10,
      "font": "CourierBold"
    },
    {
      "key": "Pt4Line3d_PostalCode",
      "originalKey": "form1[0].#subform[3].Pt4Line3d_PostalCode[0]",
      "kind": "text",
      "mode": "text",
      "page": 4,
      "x": 408.1,
      "y": 290,
      "width": 167.9,
      "height": 18,
      "size": 10,
      "font": "CourierBold"
    },
    {
      "key": "Line2f_Country",
      "originalKey": "form1[0].#subform[3].Line2f_Country[0]",
      "kind": "text",
      "mode": "text",
      "page": 4,
      "x": 342,
      "y": 254,
      "width": 234,
      "height": 18,
      "size": 10,
      "font": "CourierBold"
    },
    {
      "key": "Pt4Line3e_Province",
      "originalKey": "form1[0].#subform[3].Pt4Line3e_Province[0]",
      "kind": "text",
      "mode": "text",
      "page": 4,
      "x": 408,
      "y": 314,
      "width": 167.9,
      "height": 18,
      "size": 10,
      "font": "CourierBold"
    },
    {
      "key": "Pt4Line4_JobTitle",
      "originalKey": "form1[0].#subform[4].Pt4Line4_JobTitle[0]",
      "kind": "text",
      "mode": "text",
      "page": 5,
      "x": 60,
      "y": 548,
      "width": 234,
      "height": 18,
      "size": 10,
      "font": "CourierBold"
    },
    {
      "key": "Pt4Line5a_StartDate",
      "originalKey": "form1[0].#subform[4].Pt4Line5a_StartDate[0]",
      "kind": "text",
      "mode": "text",
      "page": 5,
      "x": 210,
      "y": 524,
      "width": 84,
      "height": 18,
      "size": 10,
      "font": "CourierBold"
    },
    {
      "key": "Pt4Line5b_EndDate",
      "originalKey": "form1[0].#subform[4].Pt4Line5b_EndDate[0]",
      "kind": "text",
      "mode": "text",
      "page": 5,
      "x": 210,
      "y": 500,
      "width": 84,
      "height": 18,
      "size": 10,
      "font": "CourierBold"
    },
    {
      "key": "Pt4Line6_JobDuties",
      "originalKey": "form1[0].#subform[4].Pt4Line6_JobDuties[0]",
      "kind": "text",
      "mode": "text",
      "page": 5,
      "x": 60,
      "y": 428,
      "width": 234,
      "height": 54,
      "size": 10,
      "font": "CourierBold"
    },
    {
      "key": "Pt4Line7_Wages",
      "originalKey": "form1[0].#subform[4].Pt4Line7_Wages[0]",
      "kind": "text",
      "mode": "text",
      "page": 5,
      "x": 192,
      "y": 404,
      "width": 102,
      "height": 18,
      "size": 10,
      "font": "CourierBold"
    },
    {
      "key": "Pt4Line8_HoursPerWeek",
      "originalKey": "form1[0].#subform[4].Pt4Line8_HoursPerWeek[0]",
      "kind": "text",
      "mode": "text",
      "page": 5,
      "x": 192,
      "y": 380,
      "width": 102,
      "height": 18,
      "size": 10,
      "font": "CourierBold"
    },
    {
      "key": "Pt4Line9_JobTitle",
      "originalKey": "form1[0].#subform[4].Pt4Line9_JobTitle[0]",
      "kind": "text",
      "mode": "text",
      "page": 5,
      "x": 60,
      "y": 314,
      "width": 234,
      "height": 18,
      "size": 10,
      "font": "CourierBold"
    },
    {
      "key": "Pt4Line10a_StartDate",
      "originalKey": "form1[0].#subform[4].Pt4Line10a_StartDate[0]",
      "kind": "text",
      "mode": "text",
      "page": 5,
      "x": 210,
      "y": 290,
      "width": 84,
      "height": 18,
      "size": 10,
      "font": "CourierBold"
    },
    {
      "key": "Pt4Line10b_EndDate",
      "originalKey": "form1[0].#subform[4].Pt4Line10b_EndDate[0]",
      "kind": "text",
      "mode": "text",
      "page": 5,
      "x": 210,
      "y": 266,
      "width": 84,
      "height": 18,
      "size": 10,
      "font": "CourierBold"
    },
    {
      "key": "Pt4Line11_JobDuties",
      "originalKey": "form1[0].#subform[4].Pt4Line11_JobDuties[0]",
      "kind": "text",
      "mode": "text",
      "page": 5,
      "x": 60,
      "y": 194,
      "width": 234,
      "height": 54,
      "size": 10,
      "font": "CourierBold"
    },
    {
      "key": "Pt4Line12_Wages",
      "originalKey": "form1[0].#subform[4].Pt4Line12_Wages[0]",
      "kind": "text",
      "mode": "text",
      "page": 5,
      "x": 192,
      "y": 170,
      "width": 102,
      "height": 18,
      "size": 10,
      "font": "CourierBold"
    },
    {
      "key": "Pt4Line13_HoursPerWeek",
      "originalKey": "form1[0].#subform[4].Pt4Line13_HoursPerWeek[0]",
      "kind": "text",
      "mode": "text",
      "page": 5,
      "x": 192,
      "y": 146,
      "width": 102,
      "height": 18,
      "size": 10,
      "font": "CourierBold"
    },
    {
      "key": "Pt5_CheckBox",
      "originalKeys": [
        "form1[0].#subform[4].Pt5_CheckBox[0]",
        "form1[0].#subform[4].Pt5_CheckBox[1]"
      ],
      "kind": "checkbox",
      "mode": "checkbox_group",
      "page": 5,
      "size": 10,
      "font": "HelveticaBold",
      "options": [
        {
          "value": 0,
          "x": 343,
          "y": 594,
          "width": 10,
          "height": 10
        },
        {
          "value": 1,
          "x": 343,
          "y": 534,
          "width": 10,
          "height": 10
        }
      ]
    },
    {
      "key": "Pt7Line3_PetitionerAuthorizedDaytimePhoneNumber1",
      "originalKey": "form1[0].#subform[4].Pt7Line3_PetitionerAuthorizedDaytimePhoneNumber1[0]",
      "kind": "text",
      "mode": "text",
      "page": 5,
      "x": 342,
      "y": 158,
      "width": 234,
      "height": 18,
      "size": 10,
      "font": "CourierBold"
    },
    {
      "key": "Pt7Line5_PetitionerAurthorizedEmail",
      "originalKey": "form1[0].#subform[4].Pt7Line5_PetitionerAurthorizedEmail[0]",
      "kind": "text",
      "mode": "text",
      "page": 5,
      "x": 342,
      "y": 62,
      "width": 234,
      "height": 18,
      "size": 10,
      "font": "CourierBold"
    },
    {
      "key": "Pt7Line4_PetitionerAuthorizedMobileNumber1",
      "originalKey": "form1[0].#subform[4].Pt7Line4_PetitionerAuthorizedMobileNumber1[0]",
      "kind": "text",
      "mode": "text",
      "page": 5,
      "x": 342,
      "y": 110,
      "width": 234,
      "height": 18,
      "size": 10,
      "font": "CourierBold"
    },
    {
      "key": "Pt7Line1_PetionerAuthorizedGivenName",
      "originalKey": "form1[0].#subform[4].Pt7Line1_PetionerAuthorizedGivenName[0]",
      "kind": "text",
      "mode": "text",
      "page": 5,
      "x": 342,
      "y": 242,
      "width": 234,
      "height": 18,
      "size": 10,
      "font": "CourierBold"
    },
    {
      "key": "Pt7Line2_PetionerAuthorizedMiddleName",
      "originalKey": "form1[0].#subform[4].Pt7Line2_PetionerAuthorizedMiddleName[0]",
      "kind": "text",
      "mode": "text",
      "page": 5,
      "x": 342,
      "y": 206,
      "width": 234,
      "height": 18,
      "size": 10,
      "font": "CourierBold"
    },
    {
      "key": "Pt7Line1_PetionerAuthorizedFamilyName",
      "originalKey": "form1[0].#subform[4].Pt7Line1_PetionerAuthorizedFamilyName[0]",
      "kind": "text",
      "mode": "text",
      "page": 5,
      "x": 342,
      "y": 290,
      "width": 234,
      "height": 18,
      "size": 10,
      "font": "CourierBold"
    },
    {
      "key": "Pt7Line6_DateofSignature",
      "originalKey": "form1[0].#subform[5].Pt7Line6_DateofSignature[0]",
      "kind": "text",
      "mode": "text",
      "page": 6,
      "x": 198,
      "y": 392,
      "width": 96,
      "height": 18,
      "size": 10,
      "font": "CourierBold"
    },
    {
      "key": "Pt7Line6_Signature",
      "originalKey": "form1[0].#subform[5].Pt7Line6_Signature[0]",
      "kind": "text",
      "mode": "text",
      "page": 6,
      "x": 60,
      "y": 416,
      "width": 234,
      "height": 18,
      "size": 10,
      "font": "CourierBold"
    },
    {
      "key": "Pt8Line2_InterpreterBusinessorOrgName",
      "originalKey": "form1[0].#subform[5].Pt8Line2_InterpreterBusinessorOrgName[0]",
      "kind": "text",
      "mode": "text",
      "page": 6,
      "x": 60.5,
      "y": 206,
      "width": 233.5,
      "height": 18,
      "size": 10,
      "font": "CourierBold"
    },
    {
      "key": "Pt8Line1_InterpreterGivenName",
      "originalKey": "form1[0].#subform[5].Pt8Line1_InterpreterGivenName[0]",
      "kind": "text",
      "mode": "text",
      "page": 6,
      "x": 60.5,
      "y": 242,
      "width": 233.5,
      "height": 18,
      "size": 10,
      "font": "CourierBold"
    },
    {
      "key": "Pt8Line1_InterpreterFamilyName",
      "originalKey": "form1[0].#subform[5].Pt8Line1_InterpreterFamilyName[0]",
      "kind": "text",
      "mode": "text",
      "page": 6,
      "x": 60.5,
      "y": 278,
      "width": 233.5,
      "height": 18,
      "size": 10,
      "font": "CourierBold"
    },
    {
      "key": "Pt8Line3_InterpreterDaytimeTelephone",
      "originalKey": "form1[0].#subform[5].#area[5].Pt8Line3_InterpreterDaytimeTelephone[0]",
      "kind": "text",
      "mode": "text",
      "page": 6,
      "x": 60,
      "y": 140,
      "width": 234,
      "height": 18,
      "size": 10,
      "font": "CourierBold"
    },
    {
      "key": "Pt8Line5_InterpreterEmail",
      "originalKey": "form1[0].#subform[5].Pt8Line5_InterpreterEmail[0]",
      "kind": "text",
      "mode": "text",
      "page": 6,
      "x": 60,
      "y": 68,
      "width": 234,
      "height": 18,
      "size": 10,
      "font": "CourierBold"
    },
    {
      "key": "Pt8Line4_InterpreterMobileTelephone",
      "originalKey": "form1[0].#subform[5].#area[6].Pt8Line4_InterpreterMobileTelephone[0]",
      "kind": "text",
      "mode": "text",
      "page": 6,
      "x": 60,
      "y": 104,
      "width": 234,
      "height": 18,
      "size": 10,
      "font": "CourierBold"
    },
    {
      "key": "Pt8Line6_DateofSignature",
      "originalKey": "form1[0].#subform[5].Pt8Line6_DateofSignature[0]",
      "kind": "text",
      "mode": "text",
      "page": 6,
      "x": 492,
      "y": 548,
      "width": 84,
      "height": 18,
      "size": 10,
      "font": "CourierBold"
    },
    {
      "key": "Pt8Line6_Signature",
      "originalKey": "form1[0].#subform[5].Pt8Line6_Signature[0]",
      "kind": "text",
      "mode": "text",
      "page": 6,
      "x": 342,
      "y": 572,
      "width": 234,
      "height": 18,
      "size": 10,
      "font": "CourierBold"
    },
    {
      "key": "Pt8_NameofLanguage",
      "originalKey": "form1[0].#subform[5].Pt8_NameofLanguage[0]",
      "kind": "text",
      "mode": "text",
      "page": 6,
      "x": 336,
      "y": 680,
      "width": 234,
      "height": 18,
      "size": 10,
      "font": "CourierBold"
    },
    {
      "key": "Pt9Line1_PreparerGivenName",
      "originalKey": "form1[0].#subform[5].Pt9Line1_PreparerGivenName[0]",
      "kind": "text",
      "mode": "text",
      "page": 6,
      "x": 342,
      "y": 368,
      "width": 234,
      "height": 18,
      "size": 10,
      "font": "CourierBold"
    },
    {
      "key": "Pt9Line1_PreparerFamilyName",
      "originalKey": "form1[0].#subform[5].Pt9Line1_PreparerFamilyName[0]",
      "kind": "text",
      "mode": "text",
      "page": 6,
      "x": 342,
      "y": 404,
      "width": 234,
      "height": 18,
      "size": 10,
      "font": "CourierBold"
    },
    {
      "key": "Pt9Line2_PreparerBusinessOrganizationName",
      "originalKey": "form1[0].#subform[5].Pt9Line2_PreparerBusinessOrganizationName[0]",
      "kind": "text",
      "mode": "text",
      "page": 6,
      "x": 342,
      "y": 332,
      "width": 234,
      "height": 18,
      "size": 10,
      "font": "CourierBold"
    },
    {
      "key": "Pt9Line4_PreparerMobileNumber",
      "originalKey": "form1[0].#subform[5].#area[7].Pt9Line4_PreparerMobileNumber[0]",
      "kind": "text",
      "mode": "text",
      "page": 6,
      "x": 342,
      "y": 230,
      "width": 234,
      "height": 18,
      "size": 10,
      "font": "CourierBold"
    },
    {
      "key": "Pt9Line3_PreparerDaytimePhoneNumber1",
      "originalKey": "form1[0].#subform[5].Line3_DaytimePhone[0].Pt9Line3_PreparerDaytimePhoneNumber1[0]",
      "kind": "text",
      "mode": "text",
      "page": 6,
      "x": 342,
      "y": 266,
      "width": 234,
      "height": 18,
      "size": 10,
      "font": "CourierBold"
    },
    {
      "key": "Pt9Line5_PreparerEmailAddress",
      "originalKey": "form1[0].#subform[5].Pt9Line5_PreparerEmailAddress[0]",
      "kind": "text",
      "mode": "text",
      "page": 6,
      "x": 342,
      "y": 194,
      "width": 234,
      "height": 18,
      "size": 10,
      "font": "CourierBold"
    },
    {
      "key": "Pt9Line6_Signature",
      "originalKey": "form1[0].#subform[6].Pt9Line6_Signature[0]",
      "kind": "text",
      "mode": "text",
      "page": 7,
      "x": 60,
      "y": 512,
      "width": 234,
      "height": 18,
      "size": 10,
      "font": "CourierBold"
    },
    {
      "key": "Pt9Line6_DateofSignature",
      "originalKey": "form1[0].#subform[6].Pt9Line6_DateofSignature[0]",
      "kind": "text",
      "mode": "text",
      "page": 7,
      "x": 210,
      "y": 488,
      "width": 84,
      "height": 18,
      "size": 10,
      "font": "CourierBold"
    },
    {
      "key": "Pt3Line1_AlienNumber",
      "originalKey": "form1[0].#subform[7].Pt3Line1_AlienNumber[1]",
      "kind": "text",
      "mode": "text",
      "page": 8,
      "x": 165,
      "y": 476,
      "width": 129,
      "height": 18,
      "size": 10,
      "font": "CourierBold"
    },
    {
      "key": "Pt10Line3a_PageNumber",
      "originalKey": "form1[0].#subform[7].Pt10Line3a_PageNumber[0]",
      "kind": "text",
      "mode": "text",
      "page": 8,
      "x": 60,
      "y": 434,
      "width": 54,
      "height": 18,
      "size": 10,
      "font": "CourierBold"
    },
    {
      "key": "Pt10Line3b_PartNumber",
      "originalKey": "form1[0].#subform[7].Pt10Line3b_PartNumber[0]",
      "kind": "text",
      "mode": "text",
      "page": 8,
      "x": 150,
      "y": 434,
      "width": 54,
      "height": 18,
      "size": 10,
      "font": "CourierBold"
    },
    {
      "key": "Pt10Line3c_ItemNumber",
      "originalKey": "form1[0].#subform[7].Pt10Line3c_ItemNumber[0]",
      "kind": "text",
      "mode": "text",
      "page": 8,
      "x": 240,
      "y": 434,
      "width": 54,
      "height": 18,
      "size": 10,
      "font": "CourierBold"
    },
    {
      "key": "Pt10Line3d_AdditionalInfo",
      "originalKey": "form1[0].#subform[7].Pt10Line3d_AdditionalInfo[0]",
      "kind": "text",
      "mode": "text",
      "page": 8,
      "x": 60,
      "y": 266,
      "width": 234,
      "height": 162,
      "size": 10,
      "font": "CourierBold"
    },
    {
      "key": "Pt10Line5a_PageNumber",
      "originalKey": "form1[0].#subform[7].Pt10Line5a_PageNumber[0]",
      "kind": "text",
      "mode": "text",
      "page": 8,
      "x": 342,
      "y": 710,
      "width": 54,
      "height": 18,
      "size": 10,
      "font": "CourierBold"
    },
    {
      "key": "Pt10Line5b_PartNumber",
      "originalKey": "form1[0].#subform[7].Pt10Line5b_PartNumber[0]",
      "kind": "text",
      "mode": "text",
      "page": 8,
      "x": 432,
      "y": 710,
      "width": 54,
      "height": 18,
      "size": 10,
      "font": "CourierBold"
    },
    {
      "key": "Pt10Line5c_ItemNumber",
      "originalKey": "form1[0].#subform[7].Pt10Line5c_ItemNumber[0]",
      "kind": "text",
      "mode": "text",
      "page": 8,
      "x": 522,
      "y": 710,
      "width": 54,
      "height": 18,
      "size": 10,
      "font": "CourierBold"
    },
    {
      "key": "Pt10Line6a_PageNumber",
      "originalKey": "form1[0].#subform[7].Pt10Line6a_PageNumber[0]",
      "kind": "text",
      "mode": "text",
      "page": 8,
      "x": 342,
      "y": 500,
      "width": 54,
      "height": 18,
      "size": 10,
      "font": "CourierBold"
    },
    {
      "key": "Pt10Line6b_PartNumber",
      "originalKey": "form1[0].#subform[7].Pt10Line6b_PartNumber[0]",
      "kind": "text",
      "mode": "text",
      "page": 8,
      "x": 432,
      "y": 500,
      "width": 54,
      "height": 18,
      "size": 10,
      "font": "CourierBold"
    },
    {
      "key": "Pt10Line6c_ItemNumber",
      "originalKey": "form1[0].#subform[7].Pt10Line6c_ItemNumber[0]",
      "kind": "text",
      "mode": "text",
      "page": 8,
      "x": 522,
      "y": 500.1,
      "width": 54,
      "height": 17.9,
      "size": 10,
      "font": "CourierBold"
    },
    {
      "key": "Pt10Line6d_AdditionalInfo",
      "originalKey": "form1[0].#subform[7].Pt10Line6d_AdditionalInfo[0]",
      "kind": "text",
      "mode": "text",
      "page": 8,
      "x": 342,
      "y": 332,
      "width": 234,
      "height": 162,
      "size": 10,
      "font": "CourierBold"
    },
    {
      "key": "Pt3Line4a_FamilyName",
      "originalKey": "form1[0].#subform[7].Pt3Line4a_FamilyName[1]",
      "kind": "text",
      "mode": "text",
      "page": 8,
      "x": 60,
      "y": 584,
      "width": 234,
      "height": 18,
      "size": 10,
      "font": "CourierBold"
    },
    {
      "key": "Pt3Line4b_GivenName",
      "originalKey": "form1[0].#subform[7].Pt3Line4b_GivenName[1]",
      "kind": "text",
      "mode": "text",
      "page": 8,
      "x": 60,
      "y": 548,
      "width": 234,
      "height": 18,
      "size": 10,
      "font": "CourierBold"
    },
    {
      "key": "Pt3Line4c_MiddleName",
      "originalKey": "form1[0].#subform[7].Pt3Line4c_MiddleName[1]",
      "kind": "text",
      "mode": "text",
      "page": 8,
      "x": 60,
      "y": 512,
      "width": 234,
      "height": 18,
      "size": 10,
      "font": "CourierBold"
    },
    {
      "key": "Pt10Line5d_AdditionalInfo",
      "originalKey": "form1[0].#subform[7].Pt10Line5d_AdditionalInfo[0]",
      "kind": "text",
      "mode": "text",
      "page": 8,
      "x": 342,
      "y": 542,
      "width": 234,
      "height": 162,
      "size": 10,
      "font": "CourierBold"
    },
    {
      "key": "Pt9Line4a_PageNumber",
      "originalKey": "form1[0].#subform[7].Pt9Line4a_PageNumber[0]",
      "kind": "text",
      "mode": "text",
      "page": 8,
      "x": 60,
      "y": 224,
      "width": 54,
      "height": 18,
      "size": 10,
      "font": "CourierBold"
    },
    {
      "key": "Pt9Line4b_PartNumber",
      "originalKey": "form1[0].#subform[7].Pt9Line4b_PartNumber[0]",
      "kind": "text",
      "mode": "text",
      "page": 8,
      "x": 150,
      "y": 224,
      "width": 54,
      "height": 18,
      "size": 10,
      "font": "CourierBold"
    },
    {
      "key": "Pt9Line4c_ItemNumber",
      "originalKey": "form1[0].#subform[7].Pt9Line4c_ItemNumber[0]",
      "kind": "text",
      "mode": "text",
      "page": 8,
      "x": 240,
      "y": 224,
      "width": 54,
      "height": 18,
      "size": 10,
      "font": "CourierBold"
    },
    {
      "key": "Pt9Line4d_AdditionalInfo",
      "originalKey": "form1[0].#subform[7].Pt9Line4d_AdditionalInfo[0]",
      "kind": "text",
      "mode": "text",
      "page": 8,
      "x": 60,
      "y": 56,
      "width": 234,
      "height": 162,
      "size": 10,
      "font": "CourierBold"
    },
    {
      "key": "Pt9Line7a_PageNumber",
      "originalKey": "form1[0].#subform[7].Pt9Line7a_PageNumber[0]",
      "kind": "text",
      "mode": "text",
      "page": 8,
      "x": 342,
      "y": 290,
      "width": 54,
      "height": 18,
      "size": 10,
      "font": "CourierBold"
    },
    {
      "key": "Pt9Line7b_PartNumber",
      "originalKey": "form1[0].#subform[7].Pt9Line7b_PartNumber[0]",
      "kind": "text",
      "mode": "text",
      "page": 8,
      "x": 432,
      "y": 290,
      "width": 54,
      "height": 18,
      "size": 10,
      "font": "CourierBold"
    },
    {
      "key": "Pt9Line7c_ItemNumber",
      "originalKey": "form1[0].#subform[7].Pt9Line7c_ItemNumber[0]",
      "kind": "text",
      "mode": "text",
      "page": 8,
      "x": 522,
      "y": 290,
      "width": 54,
      "height": 18,
      "size": 10,
      "font": "CourierBold"
    },
    {
      "key": "Pt9Line7d_AdditionalInfo",
      "originalKey": "form1[0].#subform[7].Pt9Line7d_AdditionalInfo[0]",
      "kind": "text",
      "mode": "text",
      "page": 8,
      "x": 342,
      "y": 122,
      "width": 234,
      "height": 162,
      "size": 10,
      "font": "CourierBold"
    }
  ]
}